colemen_database.py
utils/DatabaseManager.py
utils/TableDataManager.py
utils/TableManager.py
utils/generation.py
utils/local_db_management.py
utils/object_utils.py
utils/sql_utils.py
utils/table_utils.py
colemen_database_utils-1.1.14.dist-info/METADATA
colemen_database_utils-1.1.14.dist-info/WHEEL
colemen_database_utils-1.1.14.dist-info/top_level.txt
colemen_database_utils-1.1.14.dist-info/RECORD
