Metadata-Version: 2.1
Name: colemen-database-utils
Version: 1.1.14
Summary: Colemen Database Utils
Home-page: UNKNOWN
Author: Colemen Atwood
Author-email: <atwoodcolemen@gmail.com>
License: UNKNOWN
Keywords: python
Platform: UNKNOWN
Classifier: Development Status :: 3 - Alpha
Classifier: Intended Audience :: Education
Classifier: Programming Language :: Python :: 2
Classifier: Programming Language :: Python :: 3
Classifier: Operating System :: MacOS :: MacOS X
Classifier: Operating System :: Microsoft :: Windows
Requires-Dist: colemen-string-utils (>=0.0.6)
Requires-Dist: colemen-file-utils (>=0.0.10)
Requires-Dist: mysql-connector
